README.rst
setup.py
collective/__init__.py
collective.portlet.contentsearch.egg-info/PKG-INFO
collective.portlet.contentsearch.egg-info/SOURCES.txt
collective.portlet.contentsearch.egg-info/dependency_links.txt
collective.portlet.contentsearch.egg-info/entry_points.txt
collective.portlet.contentsearch.egg-info/namespace_packages.txt
collective.portlet.contentsearch.egg-info/not-zip-safe
collective.portlet.contentsearch.egg-info/requires.txt
collective.portlet.contentsearch.egg-info/top_level.txt
collective/portlet/__init__.py
collective/portlet/contentsearch/__init__.py
collective/portlet/contentsearch/configure.zcml
collective/portlet/contentsearch/contentsearchportlet.pt
collective/portlet/contentsearch/contentsearchportlet.py
collective/portlet/contentsearch/docs/CONTRIBUTORS.rst
collective/portlet/contentsearch/docs/HISTORY.rst
collective/portlet/contentsearch/docs/INSTALL.rst
collective/portlet/contentsearch/docs/LICENSE.rst
collective/portlet/contentsearch/docs/Makefile
collective/portlet/contentsearch/docs/README.rst
collective/portlet/contentsearch/docs/conf.py
collective/portlet/contentsearch/docs/index.rst
collective/portlet/contentsearch/profiles/default/metadata.xml
collective/portlet/contentsearch/profiles/default/portlets.xml
collective/portlet/contentsearch/tests/__init__.py
collective/portlet/contentsearch/tests/base.py
collective/portlet/contentsearch/tests/test_functional.py
collective/portlet/contentsearch/tests/test_setup.py
collective/portlet/contentsearch/tests/functional/browser.txt