Metadata-Version: 1.1
Name: collective.portlet.contentsearch
Version: 0.2
Summary: Adds content search portlet for Plone..
Home-page: https://github.com/collective/collective.portlet.contentsearch
Author: Taito Horiuchi
Author-email: taito.horiuchi@gmail.com
License: BSD
Platform: UNKNOWN
Classifier: Framework :: Plone
Classifier: Framework :: Plone :: 4.1
Classifier: Framework :: Plone :: 4.2
Classifier: License :: OSI Approved :: BSD License
Classifier: Programming Language :: Python
Classifier: Programming Language :: Python :: 2.7
